{"sections":{"main":{"type":"product-information","blocks":{"media-gallery":{"type":"_product-media-gallery","static":true,"settings":{"media_presentation":"grid","media_columns":"two"}},"product-details":{"type":"_product-details","static":true,"settings":{},"blocks":{"group_icgrde":{"type":"group","settings":{},"blocks":{"text_xrnftG":{"type":"text","settings":{"text":"<h1>{{ closest.product.title }}<\/h1>","type_preset":"h3"}}},"block_order":["text_xrnftG"]},"divider_VJhene":{"type":"_divider","settings":{}},"variant_picker_R3rGDr":{"type":"variant-picker","settings":{}},"inquiry_button":{"type":"button","settings":{"label":"Get a Free Quote & Solution","link":"\/pages\/contact","style_class":"button-primary"}},"download_spec":{"type":"button","settings":{"label":"Download LZ-1390 Spec Sheet (PDF)","link":"https:\/\/cdn.shopify.com\/s\/files\/1\/0824\/6319\/5356\/files\/LZ-1390_Technical_Specs.pdf?v=1775465578","open_in_new_tab":true,"style_class":"button-secondary"}},"text_aEtTtq":{"type":"text","settings":{"text":"{{ closest.product.description }}","type_preset":"rte"}}},"block_order":["group_icgrde","divider_VJhene","variant_picker_R3rGDr","inquiry_button","download_spec","text_aEtTtq"]}},"settings":{"gap":48,"padding-block-start":0,"padding-block-end":0}},"trust_bar_brands":{"type":"hero","blocks":{"heading":{"type":"text","settings":{"text":"<h3>Industrial Grade Components<\/h3>","alignment":"center","type_preset":"h3"}}},"block_order":["heading"],"name":"Elite Brand Components","settings":{"media_type_1":"image","image_1":"shopify:\/\/shop_images\/A0129c0e00e6744aea0e6db514c067f212.webp","horizontal_alignment":"center","section_width":"page-width","section_height":"small","color_scheme":"scheme-2","padding-block-start":36,"padding-block-end":10}},"trust_bar_certs":{"type":"hero","name":"Certifications","settings":{"media_type_1":"image","image_1":"shopify:\/\/shop_images\/A9e0c4b4fcc164fbfb51120da25998927E.webp","horizontal_alignment":"center","section_width":"page-width","section_height":"small","color_scheme":"scheme-2","padding-block-start":10,"padding-block-end":36}},"product_recommendations_qggXJq":{"type":"product-recommendations","settings":{"product":"{{ closest.product }}","max_products":4}}},"order":["main","trust_bar_brands","trust_bar_certs","product_recommendations_qggXJq"]}